vnpy_jomongodb/__init__.py
vnpy_jomongodb/mongo.py
vnpy_jomongodb-0.1.4.dist-info/LICENSE
vnpy_jomongodb-0.1.4.dist-info/WHEEL
vnpy_jomongodb-0.1.4.dist-info/METADATA
vnpy_jomongodb-0.1.4.dist-info/RECORD
