Metadata-Version: 2.1
Name: vnpy-jomongodb
Version: 0.1.4
Summary: 
License: MIT
Author: FangyangJz
Author-email: fangyang.jing@hotmail.com
Requires-Python: >=3.7.1,<4.0.0
Classifier: License :: OSI Approved :: MIT License
Classifier: Programming Language :: Python :: 3
Classifier: Programming Language :: Python :: 3.10
Classifier: Programming Language :: Python :: 3.8
Classifier: Programming Language :: Python :: 3.9
Requires-Dist: importlib-metadata (>=4.8.1,<5.0.0)
Requires-Dist: pandas (>=1.3.4,<2.0.0)
Requires-Dist: tzlocal (>=4.0.1,<5.0.0)
Requires-Dist: vnpy-mongodb (>=1.0.0,<2.0.0)
